filename_timestamp.py
filename_timestamp-1.0.0.dist-info/METADATA
filename_timestamp-1.0.0.dist-info/WHEEL
filename_timestamp-1.0.0.dist-info/top_level.txt
filename_timestamp-1.0.0.dist-info/RECORD
