Metadata-Version: 2.1
Name: filename-timestamp
Version: 1.0.0
Summary: timestamp for filename
Author: Sun
